[
  {
    "id": 1,
    "title": "Facebook",
    "link": "https://www.facebook.com",
    "img": "/images/facebook.png"
  },
  {
    "id": 1,
    "title": "Facebook",
    "link": "https://www.facebook.com",
    "img": "/images/facebook.png"
  },
  {
    "id": 1,
    "title": "Facebook",
    "link": "https://www.facebook.com",
    "img": "/images/facebook.png"
  },
  {
    "id": 1,
    "title": "Facebook",
    "link": "https://www.facebook.com",
    "img": "/images/facebook.png"
  },
  {
    "id": 1,
    "title": "Facebook",
    "link": "https://www.facebook.com",
    "img": "/images/facebook.png"
  }
]